nfl_scraper/README.rst
nfl_scraper/main.py
nfl_scraper/my_fantasy/__init__.py
nfl_scraper/my_fantasy/league_scrape.py
nfl_scraper/nfl/__init__.py
nfl_scraper/nfl/user_login.py
nfl_scraper/utils/__init__.py
nfl_scraper/utils/_compat.py
nfl_scraper/utils/ff_models.py
nfl_scraper-1.0.4.dist-info/LICENSE
nfl_scraper-1.0.4.dist-info/WHEEL
nfl_scraper-1.0.4.dist-info/METADATA
nfl_scraper-1.0.4.dist-info/RECORD
