Metadata-Version: 2.1
Name: nfl-scraper
Version: 1.0.4
Summary: Creating a scraper for multiple fantasy football sites
Home-page: https://github.com/DeadlyChambers/fantasy-scraper
License: MIT
Keywords: nfl,nfl_scraper,fantasy,football,myfantasy
Author: DeadlyChambers
Author-email: shanechambers85@gmail.com
Requires-Python: >=3.10,<4.0
Classifier: License :: OSI Approved :: MIT License
Classifier: Programming Language :: Python :: 3
Classifier: Programming Language :: Python :: 3.10
Requires-Dist: bs4 (>=0.0.1,<0.0.2)
Requires-Dist: html5lib (>=1.1,<2.0)
Requires-Dist: importlib-metadata (>=4.4,<5.0); python_version < "3.10"
Requires-Dist: jsonpickle (>=2.2.0,<3.0.0)
Requires-Dist: prompt-toolkit (>=3.0.30,<4.0.0)
Requires-Dist: requests (>=2.28.1,<3.0.0)
Requires-Dist: selenium (>=4.3.0,<5.0.0)
Project-URL: Repository, https://github.com/DeadlyChambers/fantasy-scraper
